MANIFEST.in
README.rst
requirements.txt
setup.py
test-requirements.txt
edison/__init__.py
edison/version.py
edison.egg-info/PKG-INFO
edison.egg-info/SOURCES.txt
edison.egg-info/dependency_links.txt
edison.egg-info/top_level.txt