Metadata-Version: 1.1
Name: edison
Version: 0.0.2
Summary: Absurdity as a Service
Home-page: https://github.com/briancline/edison
Author: Brian Cline
Author-email: brian.cline@gmail.com
License: MIT
Keywords: edison hue lightpack http api rest service absurd
Platform: UNKNOWN
Classifier: Development Status :: 1 - Planning
Classifier: License :: OSI Approved :: MIT License
Classifier: Intended Audience :: Developers
Classifier: Intended Audience :: System Administrators
Classifier: Natural Language :: English
Classifier: Operating System :: POSIX :: Linux
Classifier: Operating System :: POSIX :: AIX
Classifier: Operating System :: POSIX :: HP-UX
Classifier: Operating System :: POSIX :: IRIX
Classifier: Operating System :: POSIX :: SunOS/Solaris
Classifier: Operating System :: POSIX :: BSD :: BSD/OS
Classifier: Operating System :: POSIX :: BSD :: FreeBSD
Classifier: Operating System :: POSIX :: BSD :: NetBSD
Classifier: Operating System :: POSIX :: BSD :: OpenBSD
Classifier: Operating System :: Unix
Classifier: Environment :: Web Environment
Classifier: Programming Language :: Python
Classifier: Programming Language :: Python :: 2
Classifier: Programming Language :: Python :: 2.7
Classifier: Programming Language :: Python :: 3
Classifier: Programming Language :: Python :: 3.2
Classifier: Programming Language :: Python :: 3.3
Classifier: Topic :: Home Automation
